{
  "Entries": [
    {
      "Name": "Furniture_Human_Ruins_Chest_Small",
      "State": {
        "Custom": false,
        "AllowViewing": true,
        "Type": "container",
        "Droplist": "Yungs_HyDungeons_Skeleton_Dungeon_Common"
      },
      "Weight": 50
    },
    {
      "Name": "Furniture_Human_Ruins_Chest_Large",
      "Weight": 50,
      "State": {
        "Custom": false,
        "AllowViewing": true,
        "Type": "container",
        "Droplist": "Yungs_HyDungeons_Skeleton_Dungeon_Common"
      }
    }
  ]
}
